google/cloud/resourcemanager/__init__.py
google/cloud/resourcemanager/gapic_version.py
google/cloud/resourcemanager/py.typed
google/cloud/resourcemanager_v3/__init__.py
google/cloud/resourcemanager_v3/gapic_metadata.json
google/cloud/resourcemanager_v3/gapic_version.py
google/cloud/resourcemanager_v3/py.typed
google/cloud/resourcemanager_v3/services/__init__.py
google/cloud/resourcemanager_v3/services/folders/__init__.py
google/cloud/resourcemanager_v3/services/folders/async_client.py
google/cloud/resourcemanager_v3/services/folders/client.py
google/cloud/resourcemanager_v3/services/folders/pagers.py
google/cloud/resourcemanager_v3/services/folders/transports/__init__.py
google/cloud/resourcemanager_v3/services/folders/transports/base.py
google/cloud/resourcemanager_v3/services/folders/transports/grpc.py
google/cloud/resourcemanager_v3/services/folders/transports/grpc_asyncio.py
google/cloud/resourcemanager_v3/services/folders/transports/rest.py
google/cloud/resourcemanager_v3/services/folders/transports/rest_base.py
google/cloud/resourcemanager_v3/services/organizations/__init__.py
google/cloud/resourcemanager_v3/services/organizations/async_client.py
google/cloud/resourcemanager_v3/services/organizations/client.py
google/cloud/resourcemanager_v3/services/organizations/pagers.py
google/cloud/resourcemanager_v3/services/organizations/transports/__init__.py
google/cloud/resourcemanager_v3/services/organizations/transports/base.py
google/cloud/resourcemanager_v3/services/organizations/transports/grpc.py
google/cloud/resourcemanager_v3/services/organizations/transports/grpc_asyncio.py
google/cloud/resourcemanager_v3/services/organizations/transports/rest.py
google/cloud/resourcemanager_v3/services/organizations/transports/rest_base.py
google/cloud/resourcemanager_v3/services/projects/__init__.py
google/cloud/resourcemanager_v3/services/projects/async_client.py
google/cloud/resourcemanager_v3/services/projects/client.py
google_cloud_resource_manager-1.14.2.dist-info/LICENSE
google_cloud_resource_manager-1.14.2.dist-info/METADATA
google_cloud_resource_manager-1.14.2.dist-info/WHEEL
google_cloud_resource_manager-1.14.2.dist-info/top_level.txt
google_cloud_resource_manager-1.14.2.dist-info/RECORD
